service_template/__init__.py
service_template/main.py
service_template-0.2.0.dist-info/METADATA
service_template-0.2.0.dist-info/WHEEL
service_template-0.2.0.dist-info/entry_points.txt
service_template-0.2.0.dist-info/RECORD
