Metadata-Version: 2.4
Name: service-template
Version: 0.2.0
Summary: Add your description here
Author-email: Francis Echesi <echesisuccess01@gmail.com>
Classifier: Development Status :: 4 - Beta
Classifier: Environment :: Console
Classifier: Natural Language :: English
Classifier: Programming Language :: Python :: 3.10
Requires-Python: >=3.10
Requires-Dist: requests>=2.32.3
Requires-Dist: typer>=0.15.1
Requires-Dist: uv>=0.5.23
